haystack_duckduckgo/__about__.py
haystack_duckduckgo/__init__.py
haystack_duckduckgo-0.0.1.dist-info/METADATA
haystack_duckduckgo-0.0.1.dist-info/WHEEL
haystack_duckduckgo-0.0.1.dist-info/licenses/LICENSE
haystack_duckduckgo-0.0.1.dist-info/RECORD
