Metadata-Version: 2.1
Name: haystack-duckduckgo
Version: 0.0.1
Project-URL: Documentation, https://github.com/LLukas22/haystack-duckduckgo#readme
Project-URL: Issues, https://github.com/LLukas22/haystack-duckduckgo/issues
Project-URL: Source, https://github.com/LLukas22/haystack-duckduckgo
Author-email: Lukas Kreussel <65088241+LLukas22@users.noreply.github.com>
License-Expression: MIT
License-File: LICENSE
Classifier: Development Status :: 4 - Beta
Classifier: Programming Language :: Python
Classifier: Programming Language :: Python :: 3.7
Classifier: Programming Language :: Python :: 3.8
Classifier: Programming Language :: Python :: 3.9
Classifier: Programming Language :: Python :: 3.10
Classifier: Programming Language :: Python :: 3.11
Classifier: Programming Language :: Python :: Implementation :: CPython
Classifier: Programming Language :: Python :: Implementation :: PyPy
Requires-Python: >=3.7
Requires-Dist: duckduckgo-search>=3.8.2
Requires-Dist: farm-haystack>=1.17.0
